datconnexion/__init__.py
tests/__init__.py
datconnexion-0.0.0.dist-info/LICENSE
datconnexion-0.0.0.dist-info/METADATA
datconnexion-0.0.0.dist-info/WHEEL
datconnexion-0.0.0.dist-info/top_level.txt
datconnexion-0.0.0.dist-info/RECORD
