Metadata-Version: 2.1
Name: datconnexion
Version: 0.0.0
Summary: A python package for Dat Connexion integrations.
Home-page: https://github.com/NFI-Industries/datconnexion
Author: Chris Pryer
Author-email: christophpryer@gmail.com
License: PUBLIC
Platform: UNKNOWN
